{
  "name": "@fluentui/react-data-grid-react-window",
  "entries": [
    {
      "date": "Thu, 13 Jul 2023 21:25:40 GMT",
      "tag": "@fluentui/react-data-grid-react-window_v9.0.0-beta.37",
      "version": "9.0.0-beta.37",
      "comments": {
        "none": [
          {
            "author": "martinhochel@microsoft.com",
            "package": "@fluentui/react-data-grid-react-window",
            "commit": "8a9e1018f2abb2c7608c49d32acf44e93c43cba6",
            "comment": "chore: update devDependencies to use * for inner workspace dependencies"
          }
        ]
      }
    },
    {
      "date": "Tue, 11 Jul 2023 18:46:34 GMT",
      "tag": "@fluentui/react-data-grid-react-window_v9.0.0-beta.37",
      "version": "9.0.0-beta.37",
      "comments": {
        "prerelease": [
          {
            "author": "lingfan.gao@microsoft.com",
            "package": "@fluentui/react-data-grid-react-window",
            "commit": "f9c4ec8d19658d9314d57f890de1a0d886edc116",
            "comment": "feat: Deprecates package in favour of @fluentui-contrib/react-data-grid-react-window"
          },
          {
            "author": "beachball",
            "package": "@fluentui/react-data-grid-react-window",
            "comment": "Bump @fluentui/react-table to v9.6.0",
            "commit": "f958e7e175264e289a6ecdc5b108e826f6b34e74"
          },
          {
            "author": "beachball",
            "package": "@fluentui/react-data-grid-react-window",
            "comment": "Bump @fluentui/react-jsx-runtime to v9.0.0-alpha.11",
            "commit": "f958e7e175264e289a6ecdc5b108e826f6b34e74"
          },
          {
            "author": "beachball",
            "package": "@fluentui/react-data-grid-react-window",
            "comment": "Bump @fluentui/react-conformance-griffel to v9.0.0",
            "commit": "f958e7e175264e289a6ecdc5b108e826f6b34e74"
          },
          {
            "author": "beachball",
            "package": "@fluentui/react-data-grid-react-window",
            "comment": "Bump @fluentui/react-components to v9.26.0",
            "commit": "f958e7e175264e289a6ecdc5b108e826f6b34e74"
          }
        ]
      }
    },
    {
      "date": "Mon, 03 Jul 2023 20:43:09 GMT",
      "tag": "@fluentui/react-data-grid-react-window_v9.0.0-beta.36",
      "version": "9.0.0-beta.36",
      "comments": {
        "prerelease": [
          {
            "author": "beachball",
            "package": "@fluentui/react-data-grid-react-window",
            "comment": "Bump @fluentui/react-components to v9.25.1",
            "commit": "7b6bd85a2edbc0b9257fe300062d657a4c256844"
          }
        ]
      }
    },
    {
      "date": "Mon, 03 Jul 2023 13:34:28 GMT",
      "tag": "@fluentui/react-data-grid-react-window_v9.0.0-beta.35",
      "version": "9.0.0-beta.35",
      "comments": {
        "prerelease": [
          {
            "author": "beachball",
            "package": "@fluentui/react-data-grid-react-window",
            "comment": "Bump @fluentui/react-table to v9.5.0",
            "commit": "d2c95969c67521ea1df57e1339f8743b09b68772"
          },
          {
            "author": "beachball",
            "package": "@fluentui/react-data-grid-react-window",
            "comment": "Bump @fluentui/react-components to v9.25.0",
            "commit": "d2c95969c67521ea1df57e1339f8743b09b68772"
          }
        ]
      }
    },
    {
      "date": "Mon, 03 Jul 2023 11:57:12 GMT",
      "tag": "@fluentui/react-data-grid-react-window_v9.0.0-beta.34",
      "version": "9.0.0-beta.34",
      "comments": {
        "prerelease": [
          {
            "author": "lingfan.gao@microsoft.com",
            "package": "@fluentui/react-data-grid-react-window",
            "commit": "1745a0bfdb5ad5a0757fe57e2c698bc170a34cfe",
            "comment": "fix: Memoize virtualized renderer"
          },
          {
            "author": "beachball",
            "package": "@fluentui/react-data-grid-react-window",
            "comment": "Bump @fluentui/react-table to v9.4.4",
            "commit": "61633ba5de03e0ddf4839dba6da325e30c7ce9bd"
          },
          {
            "author": "beachball",
            "package": "@fluentui/react-data-grid-react-window",
            "comment": "Bump @fluentui/react-utilities to v9.10.1",
            "commit": "61633ba5de03e0ddf4839dba6da325e30c7ce9bd"
          },
          {
            "author": "beachball",
            "package": "@fluentui/react-data-grid-react-window",
            "comment": "Bump @fluentui/react-jsx-runtime to v9.0.0-alpha.10",
            "commit": "61633ba5de03e0ddf4839dba6da325e30c7ce9bd"
          },
          {
            "author": "beachball",
            "package": "@fluentui/react-data-grid-react-window",
            "comment": "Bump @fluentui/react-components to v9.24.0",
            "commit": "61633ba5de03e0ddf4839dba6da325e30c7ce9bd"
          }
        ]
      }
    },
    {
      "date": "Wed, 28 Jun 2023 11:12:25 GMT",
      "tag": "@fluentui/react-data-grid-react-window_v9.0.0-beta.33",
      "version": "9.0.0-beta.33",
      "comments": {
        "none": [
          {
            "author": "martinhochel@microsoft.com",
            "package": "@fluentui/react-data-grid-react-window",
            "commit": "fbe878e9c9785588197481f172c42c2c0a230292",
            "comment": "fix: update .npmignore to unify v8 packages and exclude project.json"
          }
        ],
        "prerelease": [
          {
            "author": "beachball",
            "package": "@fluentui/react-data-grid-react-window",
            "comment": "Bump @fluentui/react-table to v9.4.3",
            "commit": "08de131d5f3346e001dcd8d2f0f3809c698f16d7"
          },
          {
            "author": "beachball",
            "package": "@fluentui/react-data-grid-react-window",
            "comment": "Bump @fluentui/react-utilities to v9.10.0",
            "commit": "08de131d5f3346e001dcd8d2f0f3809c698f16d7"
          },
          {
            "author": "beachball",
            "package": "@fluentui/react-data-grid-react-window",
            "comment": "Bump @fluentui/react-jsx-runtime to v9.0.0-alpha.9",
            "commit": "08de131d5f3346e001dcd8d2f0f3809c698f16d7"
          },
          {
            "author": "beachball",
            "package": "@fluentui/react-data-grid-react-window",
            "comment": "Bump @fluentui/react-components to v9.23.1",
            "commit": "08de131d5f3346e001dcd8d2f0f3809c698f16d7"
          }
        ]
      }
    },
    {
      "date": "Tue, 27 Jun 2023 11:21:23 GMT",
      "tag": "@fluentui/react-data-grid-react-window_v9.0.0-beta.32",
      "version": "9.0.0-beta.32",
      "comments": {
        "prerelease": [
          {
            "author": "beachball",
            "package": "@fluentui/react-data-grid-react-window",
            "comment": "Bump @fluentui/react-table to v9.4.2",
            "commit": "1c7e6451a11fb9c59e344df616394a320e8031c4"
          },
          {
            "author": "beachball",
            "package": "@fluentui/react-data-grid-react-window",
            "comment": "Bump @fluentui/react-components to v9.23.0",
            "commit": "1c7e6451a11fb9c59e344df616394a320e8031c4"
          }
        ]
      }
    },
    {
      "date": "Mon, 26 Jun 2023 09:53:55 GMT",
      "tag": "@fluentui/react-data-grid-react-window_v9.0.0-beta.31",
      "version": "9.0.0-beta.31",
      "comments": {
        "prerelease": [
          {
            "author": "beachball",
            "package": "@fluentui/react-data-grid-react-window",
            "comment": "Bump @fluentui/react-table to v9.4.1",
            "commit": "3e47257676ace0598b9ed336a54befd4d063c332"
          },
          {
            "author": "beachball",
            "package": "@fluentui/react-data-grid-react-window",
            "comment": "Bump @fluentui/react-utilities to v9.9.4",
            "commit": "3e47257676ace0598b9ed336a54befd4d063c332"
          },
          {
            "author": "beachball",
            "package": "@fluentui/react-data-grid-react-window",
            "comment": "Bump @fluentui/react-jsx-runtime to v9.0.0-alpha.8",
            "commit": "3e47257676ace0598b9ed336a54befd4d063c332"
          },
          {
            "author": "beachball",
            "package": "@fluentui/react-data-grid-react-window",
            "comment": "Bump @fluentui/react-components to v9.22.1",
            "commit": "3e47257676ace0598b9ed336a54befd4d063c332"
          }
        ]
      }
    },
    {
      "date": "Tue, 20 Jun 2023 12:38:57 GMT",
      "tag": "@fluentui/react-data-grid-react-window_v9.0.0-beta.30",
      "version": "9.0.0-beta.30",
      "comments": {
        "prerelease": [
          {
            "author": "jirivyhnalek@microsoft.com",
            "package": "@fluentui/react-data-grid-react-window",
            "commit": "54316f1ded96bffa3505140ec68031afd0cebdb6",
            "comment": "Fixed an issue where columns would overflow when resizableColumns is on"
          },
          {
            "author": "beachball",
            "package": "@fluentui/react-data-grid-react-window",
            "comment": "Bump @fluentui/react-table to v9.4.0",
            "commit": "81c9b35e0830297b2aca2cece2ae67b3899c4647"
          },
          {
            "author": "beachball",
            "package": "@fluentui/react-data-grid-react-window",
            "comment": "Bump @fluentui/react-utilities to v9.9.3",
            "commit": "81c9b35e0830297b2aca2cece2ae67b3899c4647"
          },
          {
            "author": "beachball",
            "package": "@fluentui/react-data-grid-react-window",
            "comment": "Bump @fluentui/react-jsx-runtime to v9.0.0-alpha.7",
            "commit": "81c9b35e0830297b2aca2cece2ae67b3899c4647"
          },
          {
            "author": "beachball",
            "package": "@fluentui/react-data-grid-react-window",
            "comment": "Bump @fluentui/react-conformance-griffel to v9.0.0-beta.23",
            "commit": "81c9b35e0830297b2aca2cece2ae67b3899c4647"
          },
          {
            "author": "beachball",
            "package": "@fluentui/react-data-grid-react-window",
            "comment": "Bump @fluentui/react-components to v9.22.0",
            "commit": "81c9b35e0830297b2aca2cece2ae67b3899c4647"
          }
        ]
      }
    },
    {
      "date": "Wed, 31 May 2023 06:46:23 GMT",
      "tag": "@fluentui/react-data-grid-react-window_v9.0.0-beta.29",
      "version": "9.0.0-beta.29",
      "comments": {
        "prerelease": [
          {
            "author": "beachball",
            "package": "@fluentui/react-data-grid-react-window",
            "comment": "Bump @fluentui/react-table to v9.3.0",
            "commit": "17ca96c6b7f684f36a5c63e40e78b4986a86c713"
          },
          {
            "author": "beachball",
            "package": "@fluentui/react-data-grid-react-window",
            "comment": "Bump @fluentui/react-utilities to v9.9.2",
            "commit": "17ca96c6b7f684f36a5c63e40e78b4986a86c713"
          },
          {
            "author": "beachball",
            "package": "@fluentui/react-data-grid-react-window",
            "comment": "Bump @fluentui/react-jsx-runtime to v9.0.0-alpha.6",
            "commit": "17ca96c6b7f684f36a5c63e40e78b4986a86c713"
          },
          {
            "author": "beachball",
            "package": "@fluentui/react-data-grid-react-window",
            "comment": "Bump @fluentui/react-conformance-griffel to v9.0.0-beta.22",
            "commit": "17ca96c6b7f684f36a5c63e40e78b4986a86c713"
          },
          {
            "author": "beachball",
            "package": "@fluentui/react-data-grid-react-window",
            "comment": "Bump @fluentui/react-components to v9.21.0",
            "commit": "17ca96c6b7f684f36a5c63e40e78b4986a86c713"
          }
        ]
      }
    },
    {
      "date": "Thu, 25 May 2023 10:00:48 GMT",
      "tag": "@fluentui/react-data-grid-react-window_v9.0.0-beta.28",
      "version": "9.0.0-beta.28",
      "comments": {
        "prerelease": [
          {
            "author": "beachball",
            "package": "@fluentui/react-data-grid-react-window",
            "comment": "Bump @fluentui/react-table to v9.2.12",
            "commit": "8f7c1b7591b3e665ae39e1b22ab0f0b28fb795c4"
          },
          {
            "author": "beachball",
            "package": "@fluentui/react-data-grid-react-window",
            "comment": "Bump @fluentui/react-utilities to v9.9.1",
            "commit": "8f7c1b7591b3e665ae39e1b22ab0f0b28fb795c4"
          },
          {
            "author": "beachball",
            "package": "@fluentui/react-data-grid-react-window",
            "comment": "Bump @fluentui/react-jsx-runtime to v9.0.0-alpha.5",
            "commit": "8f7c1b7591b3e665ae39e1b22ab0f0b28fb795c4"
          },
          {
            "author": "beachball",
            "package": "@fluentui/react-data-grid-react-window",
            "comment": "Bump @fluentui/react-components to v9.20.4",
            "commit": "8f7c1b7591b3e665ae39e1b22ab0f0b28fb795c4"
          }
        ]
      }
    },
    {
      "date": "Wed, 24 May 2023 20:45:25 GMT",
      "tag": "@fluentui/react-data-grid-react-window_v9.0.0-beta.27",
      "version": "9.0.0-beta.27",
      "comments": {
        "none": [
          {
            "author": "olfedias@microsoft.com",
            "package": "@fluentui/react-data-grid-react-window",
            "commit": "69e0617a93cb44ef42f3bd19284b7dc5fe27fed3",
            "comment": "chore: update test-ssr script"
          }
        ],
        "prerelease": [
          {
            "author": "beachball",
            "package": "@fluentui/react-data-grid-react-window",
            "comment": "Bump @fluentui/react-table to v9.2.11",
            "commit": "3f088b7b09988e7c05af1c953021acc94c273026"
          },
          {
            "author": "beachball",
            "package": "@fluentui/react-data-grid-react-window",
            "comment": "Bump @fluentui/react-components to v9.20.3",
            "commit": "3f088b7b09988e7c05af1c953021acc94c273026"
          }
        ]
      }
    },
    {
      "date": "Thu, 18 May 2023 13:11:08 GMT",
      "tag": "@fluentui/react-data-grid-react-window_v9.0.0-beta.26",
      "version": "9.0.0-beta.26",
      "comments": {
        "prerelease": [
          {
            "author": "beachball",
            "package": "@fluentui/react-data-grid-react-window",
            "comment": "Bump @fluentui/react-table to v9.2.10",
            "commit": "1e6f5c8eec4b67c051fb3aa429e303115570ae4d"
          },
          {
            "author": "beachball",
            "package": "@fluentui/react-data-grid-react-window",
            "comment": "Bump @fluentui/react-components to v9.20.2",
            "commit": "1e6f5c8eec4b67c051fb3aa429e303115570ae4d"
          }
        ]
      }
    },
    {
      "date": "Thu, 18 May 2023 00:39:05 GMT",
      "tag": "@fluentui/react-data-grid-react-window_v9.0.0-beta.25",
      "version": "9.0.0-beta.25",
      "comments": {
        "none": [
          {
            "author": "olfedias@microsoft.com",
            "package": "@fluentui/react-data-grid-react-window",
            "commit": "06cd515eda59a3078bfe32f9cc7c1f281cd20208",
            "comment": "chore: add test-ssr script to v9 packages"
          }
        ],
        "prerelease": [
          {
            "author": "beachball",
            "package": "@fluentui/react-data-grid-react-window",
            "comment": "Bump @fluentui/react-table to v9.2.9",
            "commit": "c496a1cf1ec82c08753df72c9061e84b77b7daeb"
          },
          {
            "author": "beachball",
            "package": "@fluentui/react-data-grid-react-window",
            "comment": "Bump @fluentui/react-utilities to v9.9.0",
            "commit": "c496a1cf1ec82c08753df72c9061e84b77b7daeb"
          },
          {
            "author": "beachball",
            "package": "@fluentui/react-data-grid-react-window",
            "comment": "Bump @fluentui/react-jsx-runtime to v9.0.0-alpha.4",
            "commit": "c496a1cf1ec82c08753df72c9061e84b77b7daeb"
          },
          {
            "author": "beachball",
            "package": "@fluentui/react-data-grid-react-window",
            "comment": "Bump @fluentui/react-components to v9.20.1",
            "commit": "c496a1cf1ec82c08753df72c9061e84b77b7daeb"
          }
        ]
      }
    },
    {
      "date": "Fri, 12 May 2023 20:28:25 GMT",
      "tag": "@fluentui/react-data-grid-react-window_v9.0.0-beta.24",
      "version": "9.0.0-beta.24",
      "comments": {
        "prerelease": [
          {
            "author": "olfedias@microsoft.com",
            "package": "@fluentui/react-data-grid-react-window",
            "commit": "9d6394b6c751092fd1d4e26ccc618b5ba05086ec",
            "comment": "chore: move makeStyles() calls to .styles.ts files"
          },
          {
            "author": "olfedias@microsoft.com",
            "package": "@fluentui/react-data-grid-react-window",
            "commit": "c28decb23d191a0daaaf6d5d1832429715102129",
            "comment": "chore: exclude .swcrc from being published"
          },
          {
            "author": "beachball",
            "package": "@fluentui/react-data-grid-react-window",
            "comment": "Bump @fluentui/react-table to v9.2.8",
            "commit": "79c08ce5bbf6387b2b18ba4c3d2d5681e0177d4b"
          },
          {
            "author": "beachball",
            "package": "@fluentui/react-data-grid-react-window",
            "comment": "Bump @fluentui/react-utilities to v9.8.1",
            "commit": "79c08ce5bbf6387b2b18ba4c3d2d5681e0177d4b"
          },
          {
            "author": "beachball",
            "package": "@fluentui/react-data-grid-react-window",
            "comment": "Bump @fluentui/react-jsx-runtime to v9.0.0-alpha.3",
            "commit": "79c08ce5bbf6387b2b18ba4c3d2d5681e0177d4b"
          },
          {
            "author": "beachball",
            "package": "@fluentui/react-data-grid-react-window",
            "comment": "Bump @fluentui/react-conformance-griffel to v9.0.0-beta.21",
            "commit": "79c08ce5bbf6387b2b18ba4c3d2d5681e0177d4b"
          },
          {
            "author": "beachball",
            "package": "@fluentui/react-data-grid-react-window",
            "comment": "Bump @fluentui/react-components to v9.20.0",
            "commit": "79c08ce5bbf6387b2b18ba4c3d2d5681e0177d4b"
          }
        ],
        "none": [
          {
            "author": "martinhochel@microsoft.com",
            "package": "@fluentui/react-data-grid-react-window",
            "commit": "dbda7fa69e3000aaf8dd4a061e254ebd35198b8e",
            "comment": "fix: update npmignore files to fix npm8/node16 regression how npm publish works"
          }
        ]
      }
    },
    {
      "date": "Mon, 24 Apr 2023 08:12:33 GMT",
      "tag": "@fluentui/react-data-grid-react-window_v9.0.0-beta.23",
      "version": "9.0.0-beta.23",
      "comments": {
        "prerelease": [
          {
            "author": "bernardo.sunderhus@gmail.com",
            "package": "@fluentui/react-data-grid-react-window",
            "commit": "85c36e249b33b0bad79be4edd1a943dfc5233b11",
            "comment": "bugfix: remove caret from react-jsx-runtime prerelease dependency"
          },
          {
            "author": "beachball",
            "package": "@fluentui/react-data-grid-react-window",
            "comment": "Bump @fluentui/react-table to v9.2.7",
            "commit": "505433ac64f144c9cca456097413d6af4582e5ee"
          },
          {
            "author": "beachball",
            "package": "@fluentui/react-data-grid-react-window",
            "comment": "Bump @fluentui/react-jsx-runtime to v9.0.0-alpha.2",
            "commit": "505433ac64f144c9cca456097413d6af4582e5ee"
          },
          {
            "author": "beachball",
            "package": "@fluentui/react-data-grid-react-window",
            "comment": "Bump @fluentui/react-components to v9.19.1",
            "commit": "505433ac64f144c9cca456097413d6af4582e5ee"
          }
        ]
      }
    },
    {
      "date": "Mon, 17 Apr 2023 17:53:49 GMT",
      "tag": "@fluentui/react-data-grid-react-window_v9.0.0-beta.22",
      "version": "9.0.0-beta.22",
      "comments": {
        "prerelease": [
          {
            "author": "bernardo.sunderhus@gmail.com",
            "package": "@fluentui/react-data-grid-react-window",
            "commit": "aed714a47395773c966829e284e4ba9d1926b59c",
            "comment": "chore: adopt custom JSX pragma"
          },
          {
            "author": "beachball",
            "package": "@fluentui/react-data-grid-react-window",
            "comment": "Bump @fluentui/react-table to v9.2.6",
            "commit": "35d247e0b6a8c2b22e69942afbabe18043e59585"
          },
          {
            "author": "beachball",
            "package": "@fluentui/react-data-grid-react-window",
            "comment": "Bump @fluentui/react-utilities to v9.8.0",
            "commit": "35d247e0b6a8c2b22e69942afbabe18043e59585"
          },
          {
            "author": "beachball",
            "package": "@fluentui/react-data-grid-react-window",
            "comment": "Bump @fluentui/react-jsx-runtime to v9.0.0-alpha.1",
            "commit": "35d247e0b6a8c2b22e69942afbabe18043e59585"
          },
          {
            "author": "beachball",
            "package": "@fluentui/react-data-grid-react-window",
            "comment": "Bump @fluentui/react-components to v9.19.0",
            "commit": "35d247e0b6a8c2b22e69942afbabe18043e59585"
          }
        ]
      }
    },
    {
      "date": "Wed, 12 Apr 2023 09:31:45 GMT",
      "tag": "@fluentui/react-data-grid-react-window_v9.0.0-beta.21",
      "version": "9.0.0-beta.21",
      "comments": {
        "prerelease": [
          {
            "author": "beachball",
            "package": "@fluentui/react-data-grid-react-window",
            "comment": "Bump @fluentui/react-table to v9.2.5",
            "commit": "45cb6089b0f5f464ae0dd9e9cba7e199a9d67cd8"
          },
          {
            "author": "beachball",
            "package": "@fluentui/react-data-grid-react-window",
            "comment": "Bump @fluentui/react-utilities to v9.7.4",
            "commit": "45cb6089b0f5f464ae0dd9e9cba7e199a9d67cd8"
          },
          {
            "author": "beachball",
            "package": "@fluentui/react-data-grid-react-window",
            "comment": "Bump @fluentui/react-components to v9.18.9",
            "commit": "45cb6089b0f5f464ae0dd9e9cba7e199a9d67cd8"
          }
        ]
      }
    },
    {
      "date": "Fri, 07 Apr 2023 00:01:45 GMT",
      "tag": "@fluentui/react-data-grid-react-window_v9.0.0-beta.20",
      "version": "9.0.0-beta.20",
      "comments": {
        "prerelease": [
          {
            "author": "beachball",
            "package": "@fluentui/react-data-grid-react-window",
            "comment": "Bump @fluentui/react-table to v9.2.4",
            "commit": "7a46cab3d31a233b89b7188e994b24712af5393c"
          },
          {
            "author": "beachball",
            "package": "@fluentui/react-data-grid-react-window",
            "comment": "Bump @fluentui/react-components to v9.18.8",
            "commit": "7a46cab3d31a233b89b7188e994b24712af5393c"
          }
        ]
      }
    },
    {
      "date": "Tue, 04 Apr 2023 18:44:50 GMT",
      "tag": "@fluentui/react-data-grid-react-window_v9.0.0-beta.19",
      "version": "9.0.0-beta.19",
      "comments": {
        "prerelease": [
          {
            "author": "beachball",
            "package": "@fluentui/react-data-grid-react-window",
            "comment": "Bump @fluentui/react-table to v9.2.3",
            "commit": "6778d76bbbad7e1975c151c797f28c2708cde2ce"
          },
          {
            "author": "beachball",
            "package": "@fluentui/react-data-grid-react-window",
            "comment": "Bump @fluentui/react-utilities to v9.7.3",
            "commit": "6778d76bbbad7e1975c151c797f28c2708cde2ce"
          },
          {
            "author": "beachball",
            "package": "@fluentui/react-data-grid-react-window",
            "comment": "Bump @fluentui/react-components to v9.18.7",
            "commit": "6778d76bbbad7e1975c151c797f28c2708cde2ce"
          }
        ]
      }
    },
    {
      "date": "Fri, 24 Mar 2023 17:36:41 GMT",
      "tag": "@fluentui/react-data-grid-react-window_v9.0.0-beta.18",
      "version": "9.0.0-beta.18",
      "comments": {
        "prerelease": [
          {
            "author": "beachball",
            "package": "@fluentui/react-data-grid-react-window",
            "comment": "Bump @fluentui/react-components to v9.18.6",
            "commit": "899de68739acdff9e641a1baedec097a6bc07309"
          }
        ]
      }
    },
    {
      "date": "Fri, 24 Mar 2023 14:58:55 GMT",
      "tag": "@fluentui/react-data-grid-react-window_v9.0.0-beta.17",
      "version": "9.0.0-beta.17",
      "comments": {
        "prerelease": [
          {
            "author": "beachball",
            "package": "@fluentui/react-data-grid-react-window",
            "comment": "Bump @fluentui/react-components to v9.18.5",
            "commit": "0f198d87130e4f9fcacdaa187b850e507e0b1ec8"
          }
        ]
      }
    },
    {
      "date": "Fri, 24 Mar 2023 10:15:28 GMT",
      "tag": "@fluentui/react-data-grid-react-window_v9.0.0-beta.16",
      "version": "9.0.0-beta.16",
      "comments": {
        "prerelease": [
          {
            "author": "beachball",
            "package": "@fluentui/react-data-grid-react-window",
            "comment": "Bump @fluentui/react-components to v9.18.4",
            "commit": "8253bc378281d56e6b4e3a454c185e2ef3672d1d"
          }
        ]
      }
    },
    {
      "date": "Tue, 21 Mar 2023 21:23:31 GMT",
      "tag": "@fluentui/react-data-grid-react-window_v9.0.0-beta.15",
      "version": "9.0.0-beta.15",
      "comments": {
        "prerelease": [
          {
            "author": "tristan.watanabe@gmail.com",
            "package": "@fluentui/react-data-grid-react-window",
            "commit": "ead1c6d4c2ac3f3596b62b8cbc07b0a03041f11f",
            "comment": "fix: add node field to package.json exports map."
          },
          {
            "author": "tristan.watanabe@gmail.com",
            "package": "@fluentui/react-data-grid-react-window",
            "commit": "2fac1a139149bd13b76b1306207bc988dca9c72c",
            "comment": "chore: migrate to swc transpilation approach."
          },
          {
            "author": "beachball",
            "package": "@fluentui/react-data-grid-react-window",
            "comment": "Bump @fluentui/react-table to v9.2.2",
            "commit": "b7a26f6263c80e3253c6b8338c33b73bae33e2b5"
          },
          {
            "author": "beachball",
            "package": "@fluentui/react-data-grid-react-window",
            "comment": "Bump @fluentui/react-utilities to v9.7.2",
            "commit": "b7a26f6263c80e3253c6b8338c33b73bae33e2b5"
          },
          {
            "author": "beachball",
            "package": "@fluentui/react-data-grid-react-window",
            "comment": "Bump @fluentui/react-conformance-griffel to v9.0.0-beta.20",
            "commit": "b7a26f6263c80e3253c6b8338c33b73bae33e2b5"
          },
          {
            "author": "beachball",
            "package": "@fluentui/react-data-grid-react-window",
            "comment": "Bump @fluentui/react-components to v9.18.3",
            "commit": "b7a26f6263c80e3253c6b8338c33b73bae33e2b5"
          }
        ]
      }
    },
    {
      "date": "Thu, 16 Mar 2023 14:36:59 GMT",
      "tag": "@fluentui/react-data-grid-react-window_v9.0.0-beta.14",
      "version": "9.0.0-beta.14",
      "comments": {
        "prerelease": [
          {
            "author": "beachball",
            "package": "@fluentui/react-data-grid-react-window",
            "comment": "Bump @fluentui/react-table to v9.2.1",
            "commit": "e7dcadf7cabae6bc6811ca04a630e7d850388f81"
          },
          {
            "author": "beachball",
            "package": "@fluentui/react-data-grid-react-window",
            "comment": "Bump @fluentui/react-utilities to v9.7.1",
            "commit": "e7dcadf7cabae6bc6811ca04a630e7d850388f81"
          },
          {
            "author": "beachball",
            "package": "@fluentui/react-data-grid-react-window",
            "comment": "Bump @fluentui/react-components to v9.18.2",
            "commit": "e7dcadf7cabae6bc6811ca04a630e7d850388f81"
          }
        ]
      }
    },
    {
      "date": "Wed, 15 Mar 2023 10:19:53 GMT",
      "tag": "@fluentui/react-data-grid-react-window_v9.0.0-beta.13",
      "version": "9.0.0-beta.13",
      "comments": {
        "prerelease": [
          {
            "author": "beachball",
            "package": "@fluentui/react-data-grid-react-window",
            "comment": "Bump @fluentui/react-table to v9.2.0",
            "commit": "5da01b4766ae6d81befb7bcd588d9cf8d969e1e2"
          },
          {
            "author": "beachball",
            "package": "@fluentui/react-data-grid-react-window",
            "comment": "Bump @fluentui/react-components to v9.18.1",
            "commit": "5da01b4766ae6d81befb7bcd588d9cf8d969e1e2"
          }
        ]
      }
    },
    {
      "date": "Mon, 13 Mar 2023 08:58:26 GMT",
      "tag": "@fluentui/react-data-grid-react-window_v9.0.0-beta.12",
      "version": "9.0.0-beta.12",
      "comments": {
        "prerelease": [
          {
            "author": "beachball",
            "package": "@fluentui/react-data-grid-react-window",
            "comment": "Bump @fluentui/react-table to v9.1.2",
            "commit": "edf96a6b5d6f13843ada1400480e347b84384b8e"
          },
          {
            "author": "beachball",
            "package": "@fluentui/react-data-grid-react-window",
            "comment": "Bump @fluentui/react-utilities to v9.7.0",
            "commit": "edf96a6b5d6f13843ada1400480e347b84384b8e"
          },
          {
            "author": "beachball",
            "package": "@fluentui/react-data-grid-react-window",
            "comment": "Bump @fluentui/react-components to v9.18.0",
            "commit": "edf96a6b5d6f13843ada1400480e347b84384b8e"
          }
        ]
      }
    },
    {
      "date": "Fri, 10 Mar 2023 13:28:40 GMT",
      "tag": "@fluentui/react-data-grid-react-window_v9.0.0-beta.11",
      "version": "9.0.0-beta.11",
      "comments": {
        "prerelease": [
          {
            "author": "beachball",
            "package": "@fluentui/react-data-grid-react-window",
            "comment": "Bump @fluentui/react-components to v9.17.1",
            "commit": "4e092355bfa9457409d7fc3b4e617681bc9d3c85"
          }
        ]
      }
    },
    {
      "date": "Fri, 10 Mar 2023 07:14:01 GMT",
      "tag": "@fluentui/react-data-grid-react-window_v9.0.0-beta.10",
      "version": "9.0.0-beta.10",
      "comments": {
        "prerelease": [
          {
            "author": "beachball",
            "package": "@fluentui/react-data-grid-react-window",
            "comment": "Bump @fluentui/react-table to v9.1.1",
            "commit": "3cefc38eed17e3f37cd38fca9099cc9d700cd584"
          },
          {
            "author": "beachball",
            "package": "@fluentui/react-data-grid-react-window",
            "comment": "Bump @fluentui/react-utilities to v9.6.2",
            "commit": "3cefc38eed17e3f37cd38fca9099cc9d700cd584"
          },
          {
            "author": "beachball",
            "package": "@fluentui/react-data-grid-react-window",
            "comment": "Bump @fluentui/react-components to v9.17.0",
            "commit": "3cefc38eed17e3f37cd38fca9099cc9d700cd584"
          }
        ]
      }
    },
    {
      "date": "Wed, 08 Mar 2023 17:42:51 GMT",
      "tag": "@fluentui/react-data-grid-react-window_v9.0.0-beta.9",
      "version": "9.0.0-beta.9",
      "comments": {
        "prerelease": [
          {
            "author": "beachball",
            "package": "@fluentui/react-data-grid-react-window",
            "comment": "Bump @fluentui/react-table to v9.1.0",
            "commit": "e0d11faf97f6466f4cd23ed18266cf1e80094f56"
          },
          {
            "author": "beachball",
            "package": "@fluentui/react-data-grid-react-window",
            "comment": "Bump @fluentui/react-utilities to v9.6.1",
            "commit": "e0d11faf97f6466f4cd23ed18266cf1e80094f56"
          },
          {
            "author": "beachball",
            "package": "@fluentui/react-data-grid-react-window",
            "comment": "Bump @fluentui/react-components to v9.16.0",
            "commit": "e0d11faf97f6466f4cd23ed18266cf1e80094f56"
          }
        ]
      }
    },
    {
      "date": "Wed, 22 Feb 2023 23:06:07 GMT",
      "tag": "@fluentui/react-data-grid-react-window_v9.0.0-beta.8",
      "version": "9.0.0-beta.8",
      "comments": {
        "prerelease": [
          {
            "author": "beachball",
            "package": "@fluentui/react-data-grid-react-window",
            "comment": "Bump @fluentui/react-table to v9.0.4",
            "commit": "9ee6caa17f745e014ecba467a4528181ae49be30"
          },
          {
            "author": "beachball",
            "package": "@fluentui/react-data-grid-react-window",
            "comment": "Bump @fluentui/react-components to v9.15.6",
            "commit": "9ee6caa17f745e014ecba467a4528181ae49be30"
          }
        ]
      }
    },
    {
      "date": "Thu, 16 Feb 2023 19:18:47 GMT",
      "tag": "@fluentui/react-data-grid-react-window_v9.0.0-beta.7",
      "version": "9.0.0-beta.7",
      "comments": {
        "prerelease": [
          {
            "author": "mgodbolt@microsoft.com",
            "package": "@fluentui/react-data-grid-react-window",
            "commit": "c6f47613e95f8e43ef00792ea673d673881e14fb",
            "comment": "fixing build issues"
          },
          {
            "author": "beachball",
            "package": "@fluentui/react-data-grid-react-window",
            "comment": "Bump @fluentui/react-components to v9.15.5",
            "commit": "ca757212da6f77eb0bfe18cf7bfcc8bbab2a5da5"
          }
        ]
      }
    },
    {
      "date": "Thu, 16 Feb 2023 16:18:01 GMT",
      "tag": "@fluentui/react-data-grid-react-window_v9.0.0-beta.6",
      "version": "9.0.0-beta.6",
      "comments": {
        "prerelease": [
          {
            "author": "beachball",
            "package": "@fluentui/react-data-grid-react-window",
            "comment": "Bump @fluentui/react-components to v9.15.4",
            "commit": "4af9156bc869948b12610689f15b2a778aa690ca"
          }
        ]
      }
    },
    {
      "date": "Wed, 15 Feb 2023 11:44:52 GMT",
      "tag": "@fluentui/react-data-grid-react-window_v9.0.0-beta.5",
      "version": "9.0.0-beta.5",
      "comments": {
        "prerelease": [
          {
            "author": "beachball",
            "package": "@fluentui/react-data-grid-react-window",
            "comment": "Bump @fluentui/react-table to v9.0.3",
            "commit": "087d981aab96bef2e332a373069a19bc702a7ca2"
          },
          {
            "author": "beachball",
            "package": "@fluentui/react-data-grid-react-window",
            "comment": "Bump @fluentui/react-utilities to v9.6.0",
            "commit": "087d981aab96bef2e332a373069a19bc702a7ca2"
          },
          {
            "author": "beachball",
            "package": "@fluentui/react-data-grid-react-window",
            "comment": "Bump @fluentui/react-components to v9.15.3",
            "commit": "087d981aab96bef2e332a373069a19bc702a7ca2"
          }
        ]
      }
    },
    {
      "date": "Mon, 13 Feb 2023 23:43:14 GMT",
      "tag": "@fluentui/react-data-grid-react-window_v9.0.0-beta.4",
      "version": "9.0.0-beta.4",
      "comments": {
        "prerelease": [
          {
            "author": "beachball",
            "package": "@fluentui/react-data-grid-react-window",
            "comment": "Bump @fluentui/react-table to v9.0.2",
            "commit": "29e62b13706c2845b21d665d43cdacf1ef1b1513"
          },
          {
            "author": "beachball",
            "package": "@fluentui/react-data-grid-react-window",
            "comment": "Bump @fluentui/react-utilities to v9.5.3",
            "commit": "29e62b13706c2845b21d665d43cdacf1ef1b1513"
          },
          {
            "author": "beachball",
            "package": "@fluentui/react-data-grid-react-window",
            "comment": "Bump @fluentui/react-components to v9.15.2",
            "commit": "29e62b13706c2845b21d665d43cdacf1ef1b1513"
          }
        ]
      }
    },
    {
      "date": "Mon, 13 Feb 2023 09:35:48 GMT",
      "tag": "@fluentui/react-data-grid-react-window_v9.0.0-beta.3",
      "version": "9.0.0-beta.3",
      "comments": {
        "prerelease": [
          {
            "author": "beachball",
            "package": "@fluentui/react-data-grid-react-window",
            "comment": "Bump @fluentui/react-table to v9.0.1",
            "commit": "b24aed22677cb12a74f185feee89edefd1601b9a"
          },
          {
            "author": "beachball",
            "package": "@fluentui/react-data-grid-react-window",
            "comment": "Bump @fluentui/react-components to v9.15.1",
            "commit": "b24aed22677cb12a74f185feee89edefd1601b9a"
          }
        ]
      }
    },
    {
      "date": "Fri, 10 Feb 2023 08:50:02 GMT",
      "tag": "@fluentui/react-data-grid-react-window_v9.0.0-beta.2",
      "version": "9.0.0-beta.2",
      "comments": {
        "prerelease": [
          {
            "author": "beachball",
            "package": "@fluentui/react-data-grid-react-window",
            "comment": "Bump @fluentui/react-table to v9.0.0",
            "commit": "cc62f050f8231e8f21a2cf7dddf33003e0ba3931"
          },
          {
            "author": "beachball",
            "package": "@fluentui/react-data-grid-react-window",
            "comment": "Bump @fluentui/react-utilities to v9.5.2",
            "commit": "cc62f050f8231e8f21a2cf7dddf33003e0ba3931"
          },
          {
            "author": "beachball",
            "package": "@fluentui/react-data-grid-react-window",
            "comment": "Bump @fluentui/react-components to v9.15.0",
            "commit": "cc62f050f8231e8f21a2cf7dddf33003e0ba3931"
          }
        ]
      }
    },
    {
      "date": "Tue, 07 Feb 2023 14:13:05 GMT",
      "tag": "@fluentui/react-data-grid-react-window_v9.0.0-beta.1",
      "version": "9.0.0-beta.1",
      "comments": {
        "prerelease": [
          {
            "author": "lingfangao@hotmail.com",
            "package": "@fluentui/react-data-grid-react-window",
            "commit": "787d758ce8a3cf9eef16692969877163af8538f9",
            "comment": "feat: Initial release react-data-grid-react-window"
          },
          {
            "author": "beachball",
            "package": "@fluentui/react-data-grid-react-window",
            "comment": "Bump @fluentui/react-table to v9.0.0-rc.5",
            "commit": "8a1405562b3328c408f15e3bf511d3eb6a0c0e66"
          },
          {
            "author": "beachball",
            "package": "@fluentui/react-data-grid-react-window",
            "comment": "Bump @fluentui/react-components to v9.14.0",
            "commit": "8a1405562b3328c408f15e3bf511d3eb6a0c0e66"
          }
        ]
      }
    }
  ]
}
